Analog to Digital Convertor/design.sv
module ADC (
  input wire clk,
  input wire start,
  input wire [7:0] analog_input,
  output reg [7:0] digital_output
);

  reg [7:0] reg_value;
  reg [2:0] bit_counter;
  reg conversion_done;

  always @(posedge clk) begin
    if (start) begin
      reg_value <= 8'h00;
      bit_counter <= 3'b000;
      conversion_done <= 0;
    end else if (!conversion_done) begin
      if (bit_counter < 3'b111) begin
        reg_value[bit_counter] <= analog_input[bit_counter];
        bit_counter <= bit_counter + 1;
      end else begin
        reg_value[bit_counter] <= analog_input[bit_counter];
        digital_output <= reg_value;
        conversion_done <= 1;
      end
    end
  end

endmodule

Analog to Digital Convertor/testbench.sv
module ADC_tb;

  reg clk;
  reg start;
  reg [7:0] analog_input;
  wire [7:0] digital_output;

  // Instantiate ADC module
  ADC dut (
    .clk(clk),
    .start(start),
    .analog_input(analog_input),
    .digital_output(digital_output)
  );

  // Clock generation
  always #5 clk = ~clk;

  // Test stimulus
  initial begin
    clk = 0;
    start = 0;
    analog_input = 8'h00;

    // Apply start signal
    #10 start = 1;
    #10 start = 0;

    // Provide analog input values and capture digital outputs
    analog_input = 8'h12; // Example input value
    #50;
    analog_input = 8'hA5; // Example input value
    #50;
    // Add more input values as needed

    // Wait for conversion to complete
    #100;

    // Display digital outputs
    $display("Digital Output: %h", digital_output);

    // End simulation
    #10 $finish;
  end

  // Dump waveform variables
  initial begin
    $dumpfile("waveform.vcd");
    $dumpvars(0, ADC_tb);
  end

endmodule

Analog to Digital Convertor/waveform.vcd
$date
    Jul 12, 2023  12:30:33
$end
$version
    TOOL:	xmsim	20.09-s003
$end
$timescale
    1 ns
$end

$scope module ADC_tb $end
$var reg       1 !    clk $end
$var reg       1 "    start $end
$var reg       8 #    analog_input [7:0] $end
$var wire      8 $    digital_output [7:0] $end

$scope module dut $end
$var wire      1 %    clk  $end
$var wire      1 &    start  $end
$var wire      8 '    analog_input [7:0] $end
$var reg       8 (    digital_output [7:0] $end
$var reg       8 )    reg_value [7:0] $end
$var reg       3 *    bit_counter [2:0] $end
$var reg       1 +    conversion_done $end
$upscope $end

$upscope $end

$enddefinitions $end
$dumpvars
0!
0"
b0 #
bx $
0%
0&
b0 '
bx (
bx )
bx *
x+
$end
#5
1!
1%
#10
1"
0!
0%
1&
#15
1!
1%
b0 )
b0 *
0+
#20
0"
b10010 #
0!
0%
b10010 '
0&
#25
1!
1%
b1 *
#30
0!
0%
#35
1!
1%
b10 )
b10 *
#40
0!
0%
#45
1!
1%
b11 *
#50
0!
0%
#55
1!
1%
b100 *
#60
0!
0%
#65
1!
1%
b10010 )
b101 *
#70
b10100101 #
0!
0%
b10100101 '
#75
1!
1%
b110010 )
b110 *
#80
0!
0%
#85
1!
1%
b111 *
#90
0!
0%
#95
1!
1%
b10110010 )
b110010 (
1+
b110010 $
